{
    "dialogue": {
        "type": "template",
        "altText": "テストメッセージ",
        "template": {
            "type": "buttons",
            "text": "メッセージありがとうございます！どんなことに興味がありますか？",
            "defaultAction": {
                "type": "uri",
                "label": "Twitterをみる",
                "uri": "https://twitter.com/ky_yk_d"
            },
            "actions": [
                {
                    "type": "uri",
                    "label": "ブログを読む",
                    "uri": "https://ky-yk-d.hatenablog.com/"
                },
                {
                    "type": "uri",
                    "label": "GitHubをみる",
                    "uri": "https://github.com/ky-yk-d"
                },
                {
                    "type": "postback",
                    "label": "次の質問に行く",
                    "data": "dialogue3",
                    "displayText": "別の質問がいい！"
                }
            ]
        }
   },
   "dialogue2": {
        "type": "location",
        "title": "東京スカイツリー",
        "address": "〒131-0045 東京都墨田区押上１丁目１−２",
        "latitude": 35.710139,
        "longitude": 139.810833
   },
   "dialogue3": {
        "type": "template",
        "altText": "メッセージ",
        "template": {
            "type": "buttons",
            "thumbnailImageUrl": "https://cdn-ak.f.st-hatena.com/images/fotolife/k/ky_yk_d/20180513/20180513094057.png",
            "imageAspectRatio": "rectangle",
            "imageSize": "cover",
            "imageBackgroundColor": "#000000",
            "text": "別の質問へを押しましたね？",
            "actions": [
                {
                    "type": "postback",
                    "label": "おわり",
                    "data": "end",
                    "displayText": "おわりにする"
                },
                {
                    "type": "uri",
                    "label": "やっぱりTwitter",
                    "uri": "https://twitter.com/ky_yk_d"
                }
            ]
        }
   }
}